pyhcomet/__init__.py
pyhcomet/blends.py
pyhcomet/cases.py
pyhcomet/copyrefconfigs.py
pyhcomet/create_blend.py
pyhcomet/create_case.py
pyhcomet/create_crude_price_set.py
pyhcomet/create_price_set.py
pyhcomet/create_refinary_set.py
pyhcomet/create_report.py
pyhcomet/create_slate.py
pyhcomet/crude_price_sets.py
pyhcomet/crudes.py
pyhcomet/hcometcore.py
pyhcomet/locationmap.py
pyhcomet/netback.py
pyhcomet/price_sets.py
pyhcomet/refineries.py
pyhcomet/regions.py
pyhcomet/slates.py
tests/__init__.py
tests/conftest.py
tests/test_blends.py
tests/test_cases.py
tests/test_crude_sets.py
tests/test_crudes.py
tests/test_netback.py
tests/test_price_sets.py
tests/test_pyhcometcore.py
tests/test_refinaries.py
tests/test_regions.py
tests/test_slates.py
pyhcomet-0.0.9.dist-info/METADATA
pyhcomet-0.0.9.dist-info/WHEEL
pyhcomet-0.0.9.dist-info/top_level.txt
pyhcomet-0.0.9.dist-info/RECORD
