Metadata-Version: 2.1
Name: pyhcomet
Version: 0.0.9
Summary: Wrapper around Haverly HComet
Home-page: https://github.com/aeorxc/pyhcomet
Author: aeorxc
License: UNKNOWN
Project-URL: Source, https://github.com/aeorxc/pyhcomet
Platform: UNKNOWN
Classifier: Programming Language :: Python :: 3
Classifier: License :: OSI Approved :: MIT License
Classifier: Operating System :: OS Independent
Requires-Python: >=3.8
Requires-Dist: pandas
Requires-Dist: requests
Requires-Dist: cachetools
